obsidian_note_cli/__init__.py
obsidian_note_cli/obsidian_note_cli.py
obsidian_note_cli-0.1.5.dist-info/LICENSE
obsidian_note_cli-0.1.5.dist-info/METADATA
obsidian_note_cli-0.1.5.dist-info/WHEEL
obsidian_note_cli-0.1.5.dist-info/entry_points.txt
obsidian_note_cli-0.1.5.dist-info/RECORD
