Metadata-Version: 2.1
Name: obsidian_note_cli
Version: 0.1.5
Summary: CLI tool to save well-structured notes in Obsidian format
Home-page: https://github.com/guglielmo/obsidian_note_cli.git
Keywords: cli,note-taking,obsidian,markdown,notes,documentation,frontmatter,self-improvement,knowledge-management,zettelkasten,productivity
Author: Guglielmo Celata
Author-email: guglielmo.celata@gmail.com
Requires-Python: >=3.8,<4.0
Classifier: Development Status :: 4 - Beta
Classifier: Environment :: Console
Classifier: Intended Audience :: Developers
Classifier: Intended Audience :: End Users/Desktop
Classifier: License :: OSI Approved :: MIT License
Classifier: Operating System :: OS Independent
Classifier: Programming Language :: Python :: 3
Classifier: Programming Language :: Python :: 3.8
Classifier: Programming Language :: Python :: 3.9
Classifier: Programming Language :: Python :: 3.10
Classifier: Programming Language :: Python :: 3.11
Classifier: Programming Language :: Python :: 3.12
Classifier: Programming Language :: Python :: 3.13
Classifier: Programming Language :: Python :: 3 :: Only
Classifier: Topic :: Software Development :: Libraries :: Python Modules
Classifier: Topic :: Text Processing :: Markup
Classifier: Topic :: Text Processing :: Markup :: Markdown
Classifier: Topic :: Utilities
Requires-Dist: click (>=8.1.3,<9.0.0)
Project-URL: Repository, https://github.com/guglielmo/obsidian_note_cli.git
